flood_monitoring/__init__.py
flood_monitoring/main.py
flood_monitoring/monitor.py
tests/__init__.py
tests/test_flood_monitor.py
flood_monitoring-0.2.dist-info/LICENSE
flood_monitoring-0.2.dist-info/METADATA
flood_monitoring-0.2.dist-info/WHEEL
flood_monitoring-0.2.dist-info/entry_points.txt
flood_monitoring-0.2.dist-info/top_level.txt
flood_monitoring-0.2.dist-info/RECORD
