Metadata-Version: 2.2
Name: flood-monitoring
Version: 0.2
Summary: A simple flood monitoring package
Home-page: https://github.com/YSulehman/flood-monitoring
Author: Yusuf Sulehman
Author-email: yusuf.sulehman@postgrad.manchester.ac.uk
Classifier: Programming Language :: Python :: 3
Classifier: License :: OSI Approved :: MIT License
Classifier: Operating System :: OS Independent
Requires-Python: >=3.8
License-File: LICENSE
Requires-Dist: requests
Dynamic: author
Dynamic: author-email
Dynamic: classifier
Dynamic: description
Dynamic: description-content-type
Dynamic: home-page
Dynamic: requires-dist
Dynamic: requires-python
Dynamic: summary
